{"students":[{"id":2,"name":"阿凡达","gender":"0","age":"28","hobbies":"吃饭、睡觉、打豆豆"},{"name":"李超","gender":"0","age":"24","hobbies":"写代码，看篮球","id":3},{"name":"岳家伟","gender":"0","age":"21","hobbies":"打王者，写代码","id":4},{"name":"李镇江","gender":"0","age":"21","hobbies":"撩妹，二次元，编程","id":5},{"name":"杜鹏","gender":"0","age":"22","hobbies":"看美女，写代码","id":6},{"name":"董竹杰","gender":"0","age":"23","hobbies":"篮球，吃鸡，写代码","id":7},{"name":"陈秋燕","gender":"1","age":"23","hobbies":"画画，设计","id":8},{"name":"王梦娇","gender":"1","age":"21","hobbies":"画画，写代码，玩游戏","id":9},{"name":"沈金鹏","gender":"0","age":"21","hobbies":"打游戏，二次元，写代码，玩滑板","id":10},{"name":"大神","gender":"0","age":"22","hobbies":"写代码","id":11}]}